setup.py
django_zillow_neighborhoods/__init__.py
django_zillow_neighborhoods/admin.py
django_zillow_neighborhoods/models.py
django_zillow_neighborhoods/urls.py
django_zillow_neighborhoods/views.py
django_zillow_neighborhoods.egg-info/PKG-INFO
django_zillow_neighborhoods.egg-info/SOURCES.txt
django_zillow_neighborhoods.egg-info/dependency_links.txt
django_zillow_neighborhoods.egg-info/requires.txt
django_zillow_neighborhoods.egg-info/top_level.txt
django_zillow_neighborhoods/management/__init__.py
django_zillow_neighborhoods/management/commands/__init__.py
django_zillow_neighborhoods/management/commands/import_zillow_neighborhoods.py