Metadata-Version: 1.1
Name: django-zillow-neighborhoods
Version: 0.8.0
Summary: Django app for importing and querying Zillow's neighborhood data
Home-page: https://github.com/claymation/django-zillow-neighborhoods
Author: Clay McClure
Author-email: clay@daemons.net
License: UNKNOWN
Keywords: zillow neighborhood django geodjango postgis
Platform: UNKNOWN
Classifier: Development Status :: 4 - Beta
Classifier: Environment :: Web Environment
Classifier: Framework :: Django
Classifier: Intended Audience :: Developers
Classifier: License :: OSI Approved :: BSD License
Classifier: Topic :: Internet :: WWW/HTTP
Classifier: Topic :: Scientific/Engineering :: GIS
